luawl/__init__.py
luawl/definition.py
luawl.py-1.4.1.dist-info/LICENSE.txt
luawl.py-1.4.1.dist-info/METADATA
luawl.py-1.4.1.dist-info/WHEEL
luawl.py-1.4.1.dist-info/top_level.txt
luawl.py-1.4.1.dist-info/RECORD
