Metadata-Version: 2.1
Name: luawl.py
Version: 1.4.1
Summary: A python package specifically made for luawl!
Home-page: https://github.com/kaisei-kto/luawl.py
Author: kaisei-kto
Author-email: keshsenpai@gmail.com
License: MIT
Keywords: api
License-File: LICENSE.txt
Requires-Dist: requests
